test/__init__.py
test/test_multithreading.py
test/collections/__init__.py
test/collections/test_dict_access.py
test/collections/test_safe_dict.py
wmutils/__init__.py
wmutils/file.py
wmutils/general.py
wmutils/iterators.py
wmutils/json.py
wmutils/multithreading.py
wmutils/regex.py
wmutils/collections/__init__.py
wmutils/collections/dict_access.py
wmutils/collections/list_access.py
wmutils/collections/safe_dict.py
wmutils/pandas/__init__.py
wmutils/pandas/dataframe.py
wmutils/pandas/transforms.py
wmutils/pandas/figures/__init__.py
wmutils/pandas/figures/base.py
wmutils/pandas/figures/plots.py
wmutils/pandas/figures/pretty_plots.py
wmutils-0.13.0.dist-info/LICENSE
wmutils-0.13.0.dist-info/METADATA
wmutils-0.13.0.dist-info/WHEEL
wmutils-0.13.0.dist-info/top_level.txt
wmutils-0.13.0.dist-info/RECORD
